spider_task_monitor/__init__.py
spider_task_monitor/common/__init__.py
spider_task_monitor/common/config.py
spider_task_monitor/common/constants.py
spider_task_monitor/common/util.py
spider_task_monitor/core/__init__.py
spider_task_monitor/core/dao.py
spider_task_monitor/core/mail.py
spider_task_monitor/core/task_dao.py
spider_task_monitor/monitor/__init__.py
spider_task_monitor/monitor/monitor.py
spider_task_monitor/monitor/report.py
spider_task_monitor-0.0.8.dist-info/METADATA
spider_task_monitor-0.0.8.dist-info/RECORD
spider_task_monitor-0.0.8.dist-info/WHEEL
spider_task_monitor-0.0.8.dist-info/top_level.txt
